jupyterlab/__init__.py
jupyterlab/__main__.py
jupyterlab/_version.py
jupyterlab/browser-test.js
jupyterlab/browser_check.py
jupyterlab/commands.py
jupyterlab/coreconfig.py
jupyterlab/debuglog.py
jupyterlab/federated_labextensions.py
jupyterlab/jlpmapp.py
jupyterlab/labapp.py
jupyterlab/labextensions.py
jupyterlab/labhubapp.py
jupyterlab/node-version-check.js
jupyterlab/pytest_plugin.py
jupyterlab/semver.py
jupyterlab/serverextension.py
jupyterlab/upgrade_extension.py
jupyterlab/utils.py
jupyterlab/handlers/__init__.py
jupyterlab/handlers/build_handler.py
jupyterlab/handlers/error_handler.py
jupyterlab/handlers/extension_manager_handler.py
jupyterlab/handlers/ydoc_handler.py
jupyterlab/staging/.yarnrc
jupyterlab/staging/bootstrap.js
jupyterlab/staging/index.js
jupyterlab/staging/package.json
jupyterlab/staging/publicpath.js
jupyterlab/staging/webpack.config.js
jupyterlab/staging/webpack.prod.config.js
jupyterlab/staging/webpack.prod.minimize.config.js
jupyterlab/staging/webpack.prod.release.config.js
jupyterlab/staging/yarn.js
jupyterlab/staging/yarn.lock
jupyterlab/staging/templates/403.html
jupyterlab/staging/templates/error.html
jupyterlab/staging/templates/partial.html
jupyterlab/staging/templates/template.html
jupyterlab/tests/__init__.py
jupyterlab/tests/echo_kernel.py
jupyterlab/tests/test_app.py
jupyterlab/tests/test_build_api.py
jupyterlab/tests/test_jupyterlab.py
jupyterlab/tests/test_registry.py
jupyterlab/tests/mock_packages/extension/index.js
jupyterlab/tests/mock_packages/extension/mock_package.py
jupyterlab/tests/mock_packages/extension/package.json
jupyterlab/tests/mock_packages/extension/setup.py
jupyterlab/tests/mock_packages/incompat/index.js
jupyterlab/tests/mock_packages/incompat/package.json
jupyterlab/tests/mock_packages/interop/consumer/index.js
jupyterlab/tests/mock_packages/interop/consumer/jlab_mock_consumer.py
jupyterlab/tests/mock_packages/interop/consumer/package.json
jupyterlab/tests/mock_packages/interop/consumer/setup.py
oolab-1.1.dist-info/LICENSE
oolab-1.1.dist-info/METADATA
oolab-1.1.dist-info/WHEEL
oolab-1.1.dist-info/entry_points.txt
oolab-1.1.dist-info/top_level.txt
oolab-1.1.dist-info/RECORD
