Metadata-Version: 2.1
Name: oolab
Version: 1.1
Summary: JupyterLab computational environment
Home-page: https://jupyter.org
Author: Jupyter Development Team
Author-email: jupyter@googlegroups.com
License: UNKNOWN
Keywords: ipython,jupyter
Platform: Linux
Platform: Mac OS X
Platform: Windows
Classifier: Development Status :: 5 - Production/Stable
Classifier: Framework :: Jupyter
Classifier: Framework :: Jupyter :: JupyterLab
Classifier: Framework :: Jupyter :: JupyterLab :: 4
Classifier: Intended Audience :: Developers
Classifier: Intended Audience :: System Administrators
Classifier: Intended Audience :: Science/Research
Classifier: License :: OSI Approved :: BSD License
Classifier: Programming Language :: Python
Classifier: Programming Language :: Python :: 3.7
Classifier: Programming Language :: Python :: 3.8
Classifier: Programming Language :: Python :: 3.9
Classifier: Programming Language :: Python :: 3.10
Requires-Python: >=3.7
License-File: LICENSE
Requires-Dist: ipykernel
Requires-Dist: packaging
Requires-Dist: tornado (>=6.1.0)
Requires-Dist: jupyter-core
Requires-Dist: jupyterlab-server (<3,>=2.11.1)
Requires-Dist: jupyter-server (<2,>=1.16.0)
Requires-Dist: notebook-shim (>=0.1)
Requires-Dist: jinja2 (>=3.0.3)
Requires-Dist: ypy-websocket
Requires-Dist: jupyter-ydoc (==0.1.10)
Requires-Dist: importlib-metadata (>=3.6) ; python_version < "3.10"
Requires-Dist: importlib-resources (>=1.4) ; python_version < "3.9"
Provides-Extra: docs
Requires-Dist: sphinx (>=1.8) ; extra == 'docs'
Requires-Dist: sphinx-copybutton ; extra == 'docs'
Requires-Dist: pydata-sphinx-theme ; extra == 'docs'
Requires-Dist: pytest ; extra == 'docs'
Requires-Dist: pytest-tornasync ; extra == 'docs'
Requires-Dist: pytest-check-links ; extra == 'docs'
Requires-Dist: jsx-lexer ; extra == 'docs'
Requires-Dist: myst-parser ; extra == 'docs'
Provides-Extra: docs-screenshots
Requires-Dist: altair (==4.2.0) ; extra == 'docs-screenshots'
Requires-Dist: ipython (==8.0.0) ; extra == 'docs-screenshots'
Requires-Dist: ipywidgets (==7.6.5) ; extra == 'docs-screenshots'
Requires-Dist: jupyterlab-geojson (==3.2.0) ; extra == 'docs-screenshots'
Requires-Dist: jupyterlab-language-pack-zh-CN (==3.2.post7) ; extra == 'docs-screenshots'
Requires-Dist: matplotlib (==3.5.1) ; extra == 'docs-screenshots'
Requires-Dist: pandas (==1.3.5) ; extra == 'docs-screenshots'
Requires-Dist: scipy (==1.7.3) ; extra == 'docs-screenshots'
Requires-Dist: vdom (==0.6) ; extra == 'docs-screenshots'
Requires-Dist: vega-datasets (==0.9.0) ; extra == 'docs-screenshots'
Provides-Extra: test
Requires-Dist: check-manifest ; extra == 'test'
Requires-Dist: coverage ; extra == 'test'
Requires-Dist: jupyterlab-server[test] (<3,>=2.11.1) ; extra == 'test'
Requires-Dist: pytest (>=6.0) ; extra == 'test'
Requires-Dist: pytest-check-links (>=0.5) ; extra == 'test'
Requires-Dist: pytest-cov ; extra == 'test'
Requires-Dist: pytest-console-scripts ; extra == 'test'
Requires-Dist: requests ; extra == 'test'
Requires-Dist: requests-cache ; extra == 'test'
Requires-Dist: virtualenv ; extra == 'test'
Requires-Dist: pre-commit ; extra == 'test'
Provides-Extra: ui-tests
Requires-Dist: build ; extra == 'ui-tests'
